coffee/__init__.py
coffee/__main__.py
coffee/cli.py
coffee/manipulation.py
coffee_n_py-0.0.2.dist-info/LICENSE
coffee_n_py-0.0.2.dist-info/METADATA
coffee_n_py-0.0.2.dist-info/WHEEL
coffee_n_py-0.0.2.dist-info/entry_points.txt
coffee_n_py-0.0.2.dist-info/top_level.txt
coffee_n_py-0.0.2.dist-info/RECORD
